LICENSE.md
MANIFEST.in
README.md
setup.py
admin_atlantis/__init__.py
admin_atlantis/admin.py
admin_atlantis/apps.py
admin_atlantis/forms.py
admin_atlantis/urls.py
admin_atlantis/utils.py
admin_atlantis/views.py
admin_atlantis/migrations/__init__.py
admin_atlantis/static/assets/.gitkeep
admin_atlantis/static/assets/css/atlantis.css
admin_atlantis/static/assets/css/atlantis.min.css
admin_atlantis/static/assets/css/bootstrap.min.css
admin_atlantis/static/assets/css/demo.css
admin_atlantis/static/assets/css/fonts.css
admin_atlantis/static/assets/css/fonts.min.css
admin_atlantis/static/assets/css/forms.css
admin_atlantis/static/assets/css/style.css
admin_atlantis/static/assets/css/widgets.css
admin_atlantis/static/assets/fonts/flaticon/Flaticon.eot
admin_atlantis/static/assets/fonts/flaticon/Flaticon.svg
admin_atlantis/static/assets/fonts/flaticon/Flaticon.ttf
admin_atlantis/static/assets/fonts/flaticon/Flaticon.woff
admin_atlantis/static/assets/fonts/flaticon/_flaticon.scss
admin_atlantis/static/assets/fonts/flaticon/flaticon.css
admin_atlantis/static/assets/fonts/flaticon/flaticon.html
admin_atlantis/static/assets/fonts/fontawesome/fa-brands-400.eot
admin_atlantis/static/assets/fonts/fontawesome/fa-brands-400.svg
admin_atlantis/static/assets/fonts/fontawesome/fa-brands-400.ttf
admin_atlantis/static/assets/fonts/fontawesome/fa-brands-400.woff
admin_atlantis/static/assets/fonts/fontawesome/fa-brands-400.woff2
admin_atlantis/static/assets/fonts/fontawesome/fa-regular-400.eot
admin_atlantis/static/assets/fonts/fontawesome/fa-regular-400.svg
admin_atlantis/static/assets/fonts/fontawesome/fa-regular-400.ttf
admin_atlantis/static/assets/fonts/fontawesome/fa-regular-400.woff
admin_atlantis/static/assets/fonts/fontawesome/fa-regular-400.woff2
admin_atlantis/static/assets/fonts/fontawesome/fa-solid-900.eot
admin_atlantis/static/assets/fonts/fontawesome/fa-solid-900.svg
admin_atlantis/static/assets/fonts/fontawesome/fa-solid-900.ttf
django_admin_atlantis.egg-info/PKG-INFO
django_admin_atlantis.egg-info/SOURCES.txt
django_admin_atlantis.egg-info/dependency_links.txt
django_admin_atlantis.egg-info/not-zip-safe
django_admin_atlantis.egg-info/top_level.txt
